{
  "$schema": "https://developer.microsoft.com/json-schemas/spfx/client-side-web-part-manifest.schema.json",
  "id": "9f99ead2-8587-427d-bdfa-588960e6a6f6",
  "alias": "BannerWebPart",
  "componentType": "WebPart",
  "version": "*",
  "manifestVersion": 2,
  "requiresCustomScript": false,
  "supportedHosts": ["SharePointWebPart", "TeamsTab", "SharePointFullPage"],
  "supportsThemeVariants": true,
  "supportsFullBleed": true,
  "preconfiguredEntries": [{
    "groupId": "5c03119e-3074-46fd-976b-c60198311f70",
    "group": { "default": "Advanced" },
    "title": { "default": "Banner" },
    "description": { "default": "Banner description" },
    "officeFabricIconFontName": "Photo2",
    "properties": {
      "bannerText": "",
      "bannerImage": "",
      "bannerLink": "",
      "bannerHeight": 420,
      "useParallax": true,
      "headingFontSize": 12,
      "textFontSize": 9,
      "cardOpacity": 0.8,
      "allNewLink": "#"
    }
  }]
}
